easyData/__init__.py
easyData/data_analysis.py
easyData/exploratory_data_analysis.py
self-EDA/__init__.py
self-EDA/data_analysis.py
self-EDA/exploratory_data_analysis.py
self_EDA-0.1.0.dist-info/METADATA
self_EDA-0.1.0.dist-info/WHEEL
self_EDA-0.1.0.dist-info/top_level.txt
self_EDA-0.1.0.dist-info/RECORD
